greenbone/feed/sync/__init__.py
greenbone/feed/sync/__version__.py
greenbone/feed/sync/config.py
greenbone/feed/sync/errors.py
greenbone/feed/sync/helper.py
greenbone/feed/sync/main.py
greenbone/feed/sync/parser.py
greenbone/feed/sync/rsync.py
greenbone_feed_sync-25.2.0.dist-info/METADATA
greenbone_feed_sync-25.2.0.dist-info/WHEEL
greenbone_feed_sync-25.2.0.dist-info/entry_points.txt
greenbone_feed_sync-25.2.0.dist-info/licenses/LICENSE
greenbone_feed_sync-25.2.0.dist-info/RECORD
