Metadata-Version: 2.4
Name: greenbone-feed-sync
Version: 25.2.0
Summary: A tool for downloading the Greenbone Community Feed
License: GPL-3.0-or-later
License-File: LICENSE
Author: Björn Ricks
Author-email: bjoern.ricks@greenbone.net
Requires-Python: >=3.10,<4.0
Classifier: Development Status :: 5 - Production/Stable
Classifier: Environment :: Console
Classifier: License :: OSI Approved :: GNU General Public License v3 or later (GPLv3+)
Classifier: Operating System :: OS Independent
Classifier: Programming Language :: Python :: 3
Classifier: Programming Language :: Python :: 3.10
Classifier: Programming Language :: Python :: 3.11
Classifier: Programming Language :: Python :: 3.12
Classifier: Programming Language :: Python :: 3.13
Classifier: Programming Language :: Python :: 3.14
Classifier: Topic :: Utilities
Requires-Dist: rich (>=13.2.0)
Requires-Dist: shtab (>=1.6.5)
Requires-Dist: tomli (>=2.0.1) ; python_version < "3.11"
